csc3730TaxiDataAnalysisZhou/TaxiDataAnalysis.py
csc3730TaxiDataAnalysisZhou/__init__.py
csc3730TaxiDataAnalysisZhou-0.0.1.dist-info/METADATA
csc3730TaxiDataAnalysisZhou-0.0.1.dist-info/WHEEL
csc3730TaxiDataAnalysisZhou-0.0.1.dist-info/top_level.txt
csc3730TaxiDataAnalysisZhou-0.0.1.dist-info/RECORD
